pymantic/__init__.py
pymantic/primitives.py
pymantic/rdf.py
pymantic/serializers.py
pymantic/sparql.py
pymantic/uri_schemes.py
pymantic/util.py
pymantic/parsers/__init__.py
pymantic/parsers/base.py
pymantic/parsers/jsonld.py
pymantic/parsers/rdfxml.py
pymantic/parsers/lark/__init__.py
pymantic/parsers/lark/base.py
pymantic/parsers/lark/nquads.py
pymantic/parsers/lark/ntriples.py
pymantic/parsers/lark/turtle.py
pymantic/scripts/__init__.py
pymantic/vocab/__init__.py
pymantic/vocab/skos.py
pymantic-1.0.1.dist-info/licenses/LICENSE
pymantic-1.0.1.dist-info/METADATA
pymantic-1.0.1.dist-info/WHEEL
pymantic-1.0.1.dist-info/top_level.txt
pymantic-1.0.1.dist-info/zip-safe
pymantic-1.0.1.dist-info/RECORD
