Metadata-Version: 2.4
Name: pymantic
Version: 1.0.1
Summary: Semantic Web and RDF library for Python
Home-page: https://github.com/norcalrdf/pymantic/
Author: Gavin Carothers, Nick Pilon
Author-email: gavin@carothers.name, npilon@gmail.com
License: BSD
Keywords: RDF N3 Turtle Semantics
Classifier: Development Status :: 5 - Production/Stable
Classifier: Intended Audience :: Developers
Classifier: License :: OSI Approved :: BSD License
Classifier: Topic :: Internet :: WWW/HTTP
Classifier: Topic :: Scientific/Engineering :: Information Analysis
Classifier: Topic :: Text Processing :: Markup
Classifier: Programming Language :: Python :: 3.9
Classifier: Programming Language :: Python :: 3.10
Classifier: Programming Language :: Python :: 3.11
License-File: LICENSE
Requires-Dist: requests
Requires-Dist: lxml
Requires-Dist: pytz
Requires-Dist: rdflib
Requires-Dist: lark<1.4.0,>=1.1.0
Requires-Dist: pyld
Provides-Extra: testing
Requires-Dist: pytest; extra == "testing"
Requires-Dist: coverage; extra == "testing"
Requires-Dist: betamax; extra == "testing"
Dynamic: license-file
